audio_file_processor_mcp/__init__.py
audio_file_processor_mcp/main.py
audio_processor_mcp-0.1.5.dist-info/METADATA
audio_processor_mcp-0.1.5.dist-info/WHEEL
audio_processor_mcp-0.1.5.dist-info/entry_points.txt
audio_processor_mcp-0.1.5.dist-info/RECORD
