Metadata-Version: 2.4
Name: audio-processor-mcp
Version: 0.1.5
Summary: MCP server for audio processing: format conversion, metadata editing, volume adjustment, and audio analysis
Author-email: Your Name <your.email@example.com>
License: MIT
Keywords: audio,conversion,ffmpeg,mcp,metadata,processing,volume
Classifier: Development Status :: 4 - Beta
Classifier: Intended Audience :: Developers
Classifier: License :: OSI Approved :: MIT License
Classifier: Programming Language :: Python :: 3
Classifier: Programming Language :: Python :: 3.12
Classifier: Topic :: Multimedia :: Sound/Audio
Classifier: Topic :: Multimedia :: Sound/Audio :: Conversion
Classifier: Topic :: Software Development :: Libraries :: Python Modules
Requires-Python: >=3.12
Requires-Dist: ffmpeg-python>=0.2.0
Requires-Dist: mcp[cli]>=1.9.0
